pycnysr/__init__.py
pycnysr/pycnysr.py
pycnysr-0.0.2.dist-info/entry_points.txt
pycnysr-0.0.2.dist-info/LICENSE.md
pycnysr-0.0.2.dist-info/WHEEL
pycnysr-0.0.2.dist-info/METADATA
pycnysr-0.0.2.dist-info/RECORD
