Metadata-Version: 2.1
Name: pycnysr
Version: 0.0.2
Summary: a simple multi directory watcher and syncer
Keywords: files,synchronization,rsync,watcher
Author: Laurent Baillet
Author-email: laurent.baillet@gmail.com
Requires-Python: >=3.9,<4.0
Classifier: License :: OSI Approved :: MIT License
Classifier: Operating System :: OS Independent
Classifier: Programming Language :: Python :: 3
Classifier: Programming Language :: Python :: 3.9
Classifier: Programming Language :: Python :: 3.10
Classifier: Programming Language :: Python :: 3.11
Classifier: Programming Language :: Python :: 3
Requires-Dist: click (>=8.1.3,<9.0.0)
Requires-Dist: coverage[toml] (>=6.5.0,<7.0.0)
Requires-Dist: loguru (>=0.5.3,<0.6.0)
Requires-Dist: notify-py (>=0.3.3,<0.4.0)
Requires-Dist: pydantic (>=1.9.1,<2.0.0)
Requires-Dist: pytest-cov (>=4.0.0,<5.0.0)
Requires-Dist: pyyaml (>=6.0,<7.0)
Requires-Dist: temppathlib (>=1.2.0,<2.0.0)
Requires-Dist: types-pyyaml (>=6.0.12,<7.0.0)
Requires-Dist: watchdog (>=2.1.9,<3.0.0)
